<?xml version="1.0" encoding="UTF-8" standalone="yes"?>
<PAL1131 version="1.0">
  <PROJECT name="NoName0">
    <METRIC>
      <COMPANY><![CDATA[]]></COMPANY>
      <MANAGER><![CDATA[]]></MANAGER>
      <VERSION><![CDATA[]]></VERSION>
      <CREATED year="2010" month="11" day="2" hour="17" minutes="30" seconds="32" milisec="115" />
    </METRIC>
    <OPTIONS>
      <PV value="00000000" />
      <II value="00000038" />
      <LC year="1" month="1" day="1" hour="0" minutes="0" seconds="0" milisec="0" />
      <LCF>
        <ABSOLUTE>E:\Program Files\PAL1131\VM\VM-Praxis.xml</ABSOLUTE>
        <APPVARS>$VMsDir\VM-Praxis.xml</APPVARS>
        <ENVVARS>%ProgramFiles%\PAL1131\VM\VM-Praxis.xml</ENVVARS>
      </LCF>
    </OPTIONS>
    <LIBRARY>
      <PKG name="IEC_61131" version="131072" filename="E:\Program Files\PAL1131\Libraries\IEC 61131-3.lcp">
        <CREATED year="2009" month="11" day="24" hour="9" minutes="27" seconds="28" milisec="531" />
        <APPVARS>$LibDir\IEC 61131-3.lcp</APPVARS>
        <ENVVARS>%ProgramFiles%\PAL1131\Libraries\IEC 61131-3.lcp</ENVVARS>
        <IMP name="CTD" type="FBLK" />
        <IMP name="CTU" type="FBLK" />
        <IMP name="CTUD" type="FBLK" />
        <IMP name="F_TRIG" type="FBLK" />
        <IMP name="R_TRIG" type="FBLK" />
        <IMP name="RS" type="FBLK" />
        <IMP name="SEMA" type="FBLK" />
        <IMP name="SR" type="FBLK" />
        <IMP name="TOF" type="FBLK" />
        <IMP name="TON" type="FBLK" />
        <IMP name="TP" type="FBLK" />
      </PKG>
    </LIBRARY>
    <POU />
    <GLOBAL />
    <TASK />
  </PROJECT>
</PAL1131>